[
  {
    "_id": "1",
    "title": "كتاب البرمجة الأساسية",
    "description": "دليل شامل لتعلم أساسيات البرمجة باستخدام JavaScript. يغطي المفاهيم الأساسية مثل المتغيرات، الحلقات، والدوال.",
    "price": 50,
    "cover": "/covers/book1.jpg",
    "category": "برمجة",
    "author": "أحمد محمد",
    "pages": 200,
    "language": "العربية",
    "createdAt": "2023-01-15T10:00:00Z"
  },
  {
    "_id": "2",
    "title": "تاريخ العالم القديم",
    "description": "رحلة عبر التاريخ من العصور القديمة إلى العصور الوسطى، مع صور وخرائط توضيحية.",
    "price": 0,
    "cover": "/covers/book2.jpg",
    "category": "تاريخ",
    "author": "فاطمة علي",
    "pages": 350,
    "language": "العربية",
    "createdAt": "2023-02-20T14:30:00Z"
  },
  {
    "_id": "3",
    "title": "الذكاء الاصطناعي في الحياة اليومية",
    "description": "كيف يغير الذكاء الاصطناعي حياتنا؟ شرح مبسط للتطبيقات العملية والمستقبلية.",
    "price": 75,
    "cover": "/covers/book3.jpg",
    "category": "تكنولوجيا",
    "author": "محمد حسن",
    "pages": 180,
    "language": "العربية",
    "createdAt": "2023-03-10T09:15:00Z"
  },
  {
    "_id": "4",
    "title": "قصص الأطفال الممتعة",
    "description": "مجموعة من القصص المسلية للأطفال مع رسوم توضيحية ملونة.",
    "price": 25,
    "cover": "/covers/book4.jpg",
    "category": "أطفال",
    "author": "سارة أحمد",
    "pages": 120,
    "language": "العربية",
    "createdAt": "2023-04-05T16:45:00Z"
  },
  {
    "_id": "5",
    "title": "دليل الطبخ الشرقي",
    "description": "وصفات شهيرة من المطبخ الشرقي مع خطوات واضحة وصور للنتائج.",
    "price": 40,
    "cover": "/covers/book5.jpg",
    "category": "طبخ",
    "author": "لينا خالد",
    "pages": 250,
    "language": "العربية",
    "createdAt": "2023-05-12T11:20:00Z"
  },
  {
    "_id": "6",
    "title": "علم النفس الحديث",
    "description": "مقدمة في علم النفس مع دراسات حالة وتمارين عملية.",
    "price": 60,
    "cover": "/covers/book6.jpg",
    "category": "علم نفس",
    "author": "كريم يوسف",
    "pages": 300,
    "language": "العربية",
    "createdAt": "2023-06-18T13:00:00Z"
  },
  {
    "_id": "7",
    "title": "الرياضيات للمبتدئين",
    "description": "أساسيات الرياضيات مع أمثلة وتمارين للطلاب المبتدئين.",
    "price": 0,
    "cover": "/covers/book7.jpg",
    "category": "رياضيات",
    "author": "نور الدين سالم",
    "pages": 220,
    "language": "العربية",
    "createdAt": "2023-07-22T08:30:00Z"
  },
  {
    "_id": "8",
    "title": "أسرار النجاح في الأعمال",
    "description": "نصائح عملية لبناء أعمال ناجحة وإدارة المخاطر.",
    "price": 80,
    "cover": "/covers/book8.jpg",
    "category": "أعمال",
    "author": "عمرو فتحي",
    "pages": 280,
    "language": "العربية",
    "createdAt": "2023-08-14T15:10:00Z"
  }
]